areas/__init__.py
areas/config/architectures.py
areas/exception/__init__.py
areas/exception/compile_error.py
areas/exception/runtime_error.py
areas/exception/tool_file_error.py
areas/main.py
areas/parameters/__init__.py
areas/parameters/array_parameter.py
areas/parameters/numeric_parameter.py
areas/parameters/parameter.py
areas/parameters/string_parameter.py
areas/subroutines/__init__.py
areas/subroutines/array_subroutine.py
areas/subroutines/mixed_subroutine.py
areas/subroutines/numeric_subroutine.py
areas/subroutines/subroutine.py
areas/subroutines/void_subroutine.py
areas/test.py
areas/tester.py
areas/util/__init__.py
areas/util/parse_errors.py
areas/util/subroutine_integrity.py
areas/util/type_casting.py
areas-0.1.9.3.dist-info/LICENSE
areas-0.1.9.3.dist-info/METADATA
areas-0.1.9.3.dist-info/WHEEL
areas-0.1.9.3.dist-info/entry_points.txt
areas-0.1.9.3.dist-info/RECORD
