Metadata-Version: 2.1
Name: areas
Version: 0.1.9.3
Summary: ARM64 and RISC-V (extensible) assessment system
Home-page: https://github.com/luist18/areasear
License: MIT
Author: Luis Tavares
Author-email: luistavares10@outlook.pt
Requires-Python: >=3.9,<4.0
Classifier: License :: OSI Approved :: MIT License
Classifier: Programming Language :: Python :: 3
Classifier: Programming Language :: Python :: 3.9
Classifier: Programming Language :: Python :: 3.10
Classifier: Programming Language :: Python :: 3.11
Classifier: Programming Language :: Python :: 3.12
Requires-Dist: PyYAML (>=6.0,<7.0)
Requires-Dist: Unidecode (>=1.3.4,<2.0.0)
Requires-Dist: pytest (>=7.2.0,<8.0.0)
Project-URL: Repository, https://github.com/luist18/areasear
